MANIFEST.in
distribute_setup.py
setup.py
tox.ini
docs/build/html/developers.html
docs/build/html/history.html
docs/build/html/index.html
docs/build/html/install.html
docs/build/html/search.html
docs/build/html/searchindex.js
docs/build/html/_sources/developers.txt
docs/build/html/_sources/history.txt
docs/build/html/_sources/index.txt
docs/build/html/_sources/install.txt
docs/build/html/_static/basic.css
docs/build/html/_static/doctools.js
docs/build/html/_static/file.png
docs/build/html/_static/jquery.js
docs/build/html/_static/minus.png
docs/build/html/_static/nature.css
docs/build/html/_static/plus.png
docs/build/html/_static/pygments.css
docs/build/html/_static/searchtools.js
docs/build/html/_static/underscore.js
docs/source/conf.py
docs/source/developers.rst
docs/source/history.rst
docs/source/index.rst
docs/source/install.rst
docs/sphinx/web/templates/base.html
tests/run_tests
tests/shunit2
tests/test.sh
tests/test.sh~
tests/util.sh
virtualenvwrapper/__init__.py
virtualenvwrapper/bitbucket.py
virtualenvwrapper.bitbucket.egg-info/PKG-INFO
virtualenvwrapper.bitbucket.egg-info/SOURCES.txt
virtualenvwrapper.bitbucket.egg-info/dependency_links.txt
virtualenvwrapper.bitbucket.egg-info/entry_points.txt
virtualenvwrapper.bitbucket.egg-info/namespace_packages.txt
virtualenvwrapper.bitbucket.egg-info/not-zip-safe
virtualenvwrapper.bitbucket.egg-info/top_level.txt