Metadata-Version: 1.1
Name: virtualenvwrapper.bitbucket
Version: 2.0
Summary: virtualenvwrapper plugin to manage a project work directory based on a BitBucket repository
Home-page: http://www.doughellmann.com/projects/virtualenvwrapper.bitbucket/
Author: Doug Hellmann
Author-email: doug.hellmann@gmail.com
License: UNKNOWN
Download-URL: http://www.doughellmann.com/downloads/virtualenvwrapper.bitbucket-2.0.tar.gz
Platform: Any
Classifier: Development Status :: 5 - Production/Stable
Classifier: License :: OSI Approved :: BSD License
Classifier: Intended Audience :: Developers
Classifier: Environment :: Console
Classifier: Programming Language :: Python :: 2
Classifier: Programming Language :: Python :: 2.6
Classifier: Programming Language :: Python :: 2.7
Classifier: Programming Language :: Python :: 3
Classifier: Programming Language :: Python :: 3.2
Classifier: Programming Language :: Python :: 3.3
Requires: virtualenv
Requires: virtualenvwrapper (>=4.0)
Requires: mercurial
Provides: virtualenvwrapper.bitbucket
